iotreports_client/__init__.py
iotreports_client/api_client.py
iotreports_client/configuration.py
iotreports_client/exceptions.py
iotreports_client/helpers.py
iotreports_client/model_utils.py
iotreports_client/rest.py
iotreports_client/api/__init__.py
iotreports_client/api/category_api.py
iotreports_client/api/organization_api.py
iotreports_client/api/permissions_api.py
iotreports_client/api/report_api.py
iotreports_client/api/report_type_api.py
iotreports_client/api/user_api.py
iotreports_client/apis/__init__.py
iotreports_client/model/__init__.py
iotreports_client/model/api_token.py
iotreports_client/model/category.py
iotreports_client/model/credentials.py
iotreports_client/model/inline_response200.py
iotreports_client/model/inline_response2001.py
iotreports_client/model/inline_response2002.py
iotreports_client/model/inline_response2003.py
iotreports_client/model/inline_response2004.py
iotreports_client/model/inline_response2005.py
iotreports_client/model/inline_response2006.py
iotreports_client/model/inline_response2007.py
iotreports_client/model/inline_response2008.py
iotreports_client/model/organization.py
iotreports_client/model/permissions.py
iotreports_client/model/permissions_response.py
iotreports_client/model/report.py
iotreports_client/model/report_stream_payload.py
iotreports_client/model/report_type.py
iotreports_client/models/__init__.py
iotreports_client-1.1.0.dist-info/METADATA
iotreports_client-1.1.0.dist-info/WHEEL
iotreports_client-1.1.0.dist-info/top_level.txt
iotreports_client-1.1.0.dist-info/RECORD
